Automatic_Hook/__init__.py
Automatic_Hook/check.py
Automatic_Hook/hook.py
Automatic_Hook/utils.py
automatic_hook-0.2.0.dist-info/METADATA
automatic_hook-0.2.0.dist-info/WHEEL
automatic_hook-0.2.0.dist-info/RECORD
