Metadata-Version: 2.1
Name: Automatic_Hook
Version: 0.2.0
Summary: make any model compatible with transformer_lens
Home-page: https://github.com/HP2706/Automatic_Hook.git
License: MIT
Author: HP
Author-email: hprjdk@gmail.com
Requires-Python: >=3.11,<4.0
Classifier: License :: OSI Approved :: MIT License
Classifier: Programming Language :: Python :: 3
Classifier: Programming Language :: Python :: 3.11
Classifier: Programming Language :: Python :: 3.12
Requires-Dist: torch (>=2.0.1,<3.0.0)
Requires-Dist: transformer_lens (>=2.2.2,<3.0.0)
Requires-Dist: transformers (>=4.26.1,<5.0.0)
Project-URL: Repository, https://github.com/HP2706/Automatic_Hook.git
